<?xml version="1.0" encoding="UTF-8" ?>
<CycloneDDS xmlns="https://cdds.io/config">
  <Domain id="any">
    <General>
      <Interfaces>
        <!-- Replace address with your VM host-only adapter IPv4 -->
        <NetworkInterface address="192.168.147.128" />
      </Interfaces>
      <AllowMulticast>false</AllowMulticast>
      <MaxMessageSize>65500B</MaxMessageSize>
    </General>
    <Discovery>
      <ParticipantIndex>auto</ParticipantIndex>
      <Peers>
        <!-- VM local peers: keep local node discovery stable when multicast is disabled -->
        <Peer Address="127.0.0.1" />
        <Peer Address="192.168.147.128" />
        <!-- Replace address with your Windows host-only adapter IPv4 -->
        <Peer Address="192.168.147.1" />
      </Peers>
    </Discovery>
  </Domain>
</CycloneDDS>
